src/location_properties_pkg/LocationHandler.py
src/location_properties_pkg/__init__.py
location_handler-0.0.2.dist-info/METADATA
location_handler-0.0.2.dist-info/WHEEL
location_handler-0.0.2.dist-info/licenses/LICENSE
location_handler-0.0.2.dist-info/RECORD
